{
  "id": "waw-7301-25",
  "name": "Buzo peluche camuflado con capucha - Talle 25",
  "slug": "waw-7301-25",
  "brand": "Waw Pets",
  "category": "ropa",
  "subcategory": "Buzos",
  "price": 24610,
  "inStock": true,
  "leadTime": "24-72 hs",
  "variants": [
    {
      "label": "Camuflado verde",
      "value": "camuflado-verde",
      "color": "CAMUFLADO VERDE",
      "available": true
    },
    {
      "label": "Camuflado gris",
      "value": "camuflado-gris",
      "color": "CAMUFLADO GRIS",
      "available": false
    },
    {
      "label": "Rayado  fucsia",
      "value": "rayado-fucsia",
      "color": "RAYADO  FUCSIA",
      "available": true
    }
  ],
  "details": [
    {
      "label": "Largo Lomo",
      "value": "25 cm"
    },
    {
      "label": "Cont. Pecho",
      "value": "34 cm"
    },
    {
      "label": "Cont. Cuello",
      "value": "24 cm"
    }
  ],
  "image": "https://images.unsplash.com/photo-1583511655857-d19b40a7a54e?auto=format&fit=crop&q=80&w=800"
}